[
  {
  "name" : "pichenettes",
  "urls" : ["https://github.com/pichenettes"],
  "descriptions" : ["Mutable Instruments / émilie gillet"],
  "repos": [{
    "name" : "eurorack",
    "url" : "https://github.com/pichenettes/eurorack",
    "links" : [],
    "descriptions" : [
      "**Mutable Instruments' Eurorack Modules**",
      " * **Blinds**: Quad VC-polarizer.",
      " * **Braids**: Macro-oscillator. ",
      " * **Branches**: Dual Bernoulli gate.",
      " * **Clouds**: Texture synthesizer.",
      " * **Ears**: Contact microphone. ",
      " * **Edges**: Quad chiptune digital oscillator.",
      " * **Elements**: Modal synthesizer.",
      " * **Frames**: Keyframer/mixer.",
      " * **Grids**: Topographic drum sequencer.",
      " * **Kinks**: Utility module - rectifier, analog logic, S&H, noise.",
      " * **Links**: Utility module - buffer, mixer.",
      " * **Marbles**: Random sampler.",
      " * **Peaks**: Dual trigger converter.",
      " * **Plaits**: Macro oscillator. ",
      " * **Rings**: Resonator. ",
      " * **Ripples**: Liquid 2-pole BP, 2-pole LP and 4-pole LP filter.",
      " * **Shades**: Triple attenuverter.",
      " * **Shelves**: EQ filter. ",
      " * **Stages**: Segment generator.",
      " * **Streams**: Dual dynamics gate.",
      " * **Tides**: Tidal modulator. ",
      " * **Veils**: Quad VCA.",
      " * **Volts**: +5V power module.",
      " * **Warps**: Meta-modulator.",
      " * **Yarns**: MIDI interface."
    ],
    "images" :  [
      {
        "name": "blinds",
        "url": "https://mutable-instruments.net/modules/blinds/images/front_small.jpg",
        "description": "Quad VC-polarizer"
      },
      {
        "name": "braids",
        "url": "https://mutable-instruments.net/modules/braids/images/front_small.jpg",
        "description": "Macro-oscillator"
      },
      {
        "name": "branches",
        "url": "https://mutable-instruments.net/modules/branches/images/front_small.jpg",
        "description": "Dual Bernoulli gate"
      },
      {
        "name": "clouds",
        "url": "https://mutable-instruments.net/modules/clouds/images/front_small.jpg",
        "description": "Texture synthesizer"
      },
      {
        "name": "ears",
        "url": "https://mutable-instruments.net/modules/ears/images/front_small.jpg",
        "description": "Contact microphone"
      },
      {
        "name": "edges",
        "url": "https://mutable-instruments.net/modules/edges/images/front_small.jpg",
        "description": "Quad chiptune digital oscillator"
      },
      {
        "name": "elements",
        "url": "https://mutable-instruments.net/modules/elements/images/front_small.jpg",
        "description": "Modal synthesizer"
      },
      {
        "name": "frames",
        "url": "https://mutable-instruments.net/modules/frames/images/front_small.jpg",
        "description": "Keyframer/mixer"
      },
      {
        "name": "grids",
        "url": "https://mutable-instruments.net/modules/grids/images/front_small.jpg",
        "description": "Topographic drum sequencer"
      },
      {
        "name": "kinks",
        "url": "https://mutable-instruments.net/modules/kinks/images/front_small.jpg",
        "description": "Utility module - rectifier, analog logic, S&H, noise"
      },
      {
        "name": "links",
        "url": "https://mutable-instruments.net/modules/links/images/front_small.jpg",
        "description": "Utility module - buffer, mixer"
      },
      {
        "name": "marbles",
        "url": "https://mutable-instruments.net/modules/marbles/images/front_small.jpg",
        "description": "Random sampler"
      },
      {
        "name": "peaks",
        "url": "https://mutable-instruments.net/modules/peaks/images/front_small.jpg",
        "description": "Dual trigger converter"
      },
      {
        "name": "plaits",
        "url": "https://mutable-instruments.net/modules/plaits/images/front_small.jpg",
        "description": "Macro oscillator."
      },
      {
        "name": "rings",
        "url": "https://mutable-instruments.net/modules/rings/images/front_small.jpg",
        "description": "Resonator"
      },
      {
        "name": "ripples",
        "url": "https://mutable-instruments.net/modules/ripples/images/front_small.jpg",
        "description": "Liquid 2-pole BP, 2-pole LP and 4-pole LP filter"
      },
      {
        "name": "shades",
        "url": "https://mutable-instruments.net/modules/shades/images/front_small.jpg",
        "description": "Triple attenuverter"
      },
      {
        "name": "shelves",
        "url": "https://mutable-instruments.net/modules/shelves/images/front_small.jpg",
        "description": "EQ filter"
      },
      {
        "name": "stages",
        "url": "https://mutable-instruments.net/modules/stages/images/front_small.jpg",
        "description": "Segment generator"
      },
      {
        "name": "streams",
        "url": "https://mutable-instruments.net/modules/streams/images/front_small.jpg",
        "description": "Dual dynamics gate"
      },
      {
        "name": "tides",
        "url": "https://mutable-instruments.net/modules/tides/images/front_small.jpg",
        "description": "Tidal modulator"
      },
      {
        "name": "veils",
        "url": "https://mutable-instruments.net/modules/veils/images/front_small.jpg",
        "description": "Quad VCA"
      },
      {
        "name": "warps",
        "url": "https://mutable-instruments.net/modules/warps/images/front_small.jpg",
        "description": "Meta-modulator"
      },
      {
        "name": "yarns",
        "url": "https://mutable-instruments.net/modules/yarns/images/front_small.jpg",
        "description": "MIDI interface"
      }
    ]
  }]
},
  {
    "name" : "erica-synths",
    "urls" : ["https://github.com/erica-synths"],
    "descriptions" : [],
    "repos": [
      {
        "name" : "diy-eurorack",
        "url" : "https://github.com/erica-synths/diy-eurorack",
        "links" : [],
        "descriptions" : [
          "**Erica Synths DIY Eurorack Modules**",
          " * **Bassline**: all in one synth voice for acid basslines and drones",
          " * **BBD delay/flanger**: all analogue effects unit based on V3205 BBD IC",
          " * **Delay**: tape and digital delay unit with tap tempo, tempo sync, reverse, hold and add functions",
          " * **Dual VCA**: Polivoks architecture inspired dual VCA, rare Russian differential opamps are now replaced with AS3360",
          " * **Envelope**: recreation of Polivoks envelope generator with loop and end of attack functions",
          " * **MIDI-CV**: Polivoks functionality inspired dual MIDI-CV converter with glide function",
          " * **Mixer**: simple 3 chanel audio mixer",
          " * **Modulator**: Polivoks functionality inspired LFO, noise and S&H module",
          " * **Output**: Output module with headphone amplifier",
          " * **Polivoks VCF**: authentic recreation of the Polivoks VCF",
          " * **Swamp**: our take of Wogglebug module with lots of unique extras",
          " * **VCO3**: Polivoks inspired VCO with nice extra – VCO Sync input"
        ],
        "images" : [{
          "name": "erica-synths",
          "url": "https://www.ericasynths.lv/media/DIY_Bassline_prew.jpg.240x385_q100_crop.jpg",
          "description": "Bassline"
        },
          {
            "name": "erica-synths",
            "url": "https://www.ericasynths.lv/media/DIY_stereo_delay_prew.jpg.210x385_q100_crop.jpg",
            "description": "BBD delay/flanger"
          },
          {
            "name": "erica-synths",
            "url": "https://www.ericasynths.lv/media/DIY_DELAY_visual_2.1.jpg.210x385_q100_crop.jpg",
            "description": "Delay"
          },
          {
            "name": "erica-synths",
            "url": "https://www.ericasynths.lv/media/diy_polivoks_vca.png.120x385_q100_crop.png",
            "description": "Dual VCA"
          },
          {
            "name": "erica-synths",
            "url": "https://www.ericasynths.lv/media/diy_envelope.png.120x385_q100_crop.png",
            "description": "Envelope"
          },
          {
            "name": "erica-synths",
            "url": "https://www.ericasynths.lv/media/diy_midi_cv.png.90x385_q100_crop.png",
            "description": "MIDI-CV"
          },
          {
            "name": "erica-synths",
            "url": "https://www.ericasynths.lv/media/diy_mixer.png.90x385_q100_crop.png",
            "description": "Mixer"
          },
          {
            "name": "erica-synths",
            "url": "https://www.ericasynths.lv/media/diy_modulator.png.120x385_q100_crop.png",
            "description": "Modulator"
          },
          {
            "name": "erica-synths",
            "url": "https://www.ericasynths.lv/media/diy_output.png.90x385_q100_crop.png",
            "description": "Output"
          },
          {
            "name": "erica-synths",
            "url": "https://www.ericasynths.lv/media/diy_polivoks_vcf.png.150x385_q100_crop.png",
            "description": "Polivoks VCF"
          },
          {
            "name": "erica-synths",
            "url": "https://www.ericasynths.lv/media/diy_SWAMP.png.210x385_q100_crop.png",
            "description": "Swamp"
          },
          {
            "name": "erica-synths",
            "url": "https://www.ericasynths.lv/media/diy_polivoks_vcf.png.150x385_q100_crop.png",
            "description": "VCO3"
          }]
      }]
  },
  {
    "name" : "forestcaver",
    "urls" : ["https://github.com/shaduzlabs"],
    "descriptions" : [],
    "repos": [{
      "name" : "Analog-Voice",
      "url" : "https://github.com/forestcaver/Analog-Voice",
      "links" : [],
      "descriptions" : [
        "**analog voice modules**",
        " * **3340 VCO**",
        " * **3320 LPF**",
        " * **Phones** (Headphone Amp)",
        " * **LPG**",
        " * **HPF**",
        " * **Dual ASR**",
        " * **Dual VCA**",
        " * **Wasp**",
        " * **ADSR**",
        " * **LPF 2**",
        " * **Module Tester Module**",
        " * **Dual polarising VCA**",
        " * **Matrix Mixer**",
        " * **TZFM VCO**"
      ],
      "images" : [
        {
          "name": "forestcaver",
          "url": "https://raw.githubusercontent.com/forestcaver/Analog-Voice/master/images/3340_vco.jpg",
          "description": "3340 VCO"
        },
        {
          "name": "forestcaver",
          "url": "https://raw.githubusercontent.com/forestcaver/Analog-Voice/master/images/3320_lpf.jpg",
          "description": "3320 LPF"
        },
        {
          "name": "forestcaver",
          "url": "https://raw.githubusercontent.com/forestcaver/Analog-Voice/master/images/AJH_Phones.jpg",
          "description": "Phones (Headphone Amp)"
        },
        {
          "name": "forestcaver",
          "url": "https://raw.githubusercontent.com/forestcaver/Analog-Voice/master/images/AJH_lpg.jpg",
          "description": "LPG"
        },
        {
          "name": "forestcaver",
          "url": "https://raw.githubusercontent.com/forestcaver/Analog-Voice/master/images/3320_hpf.jpg",
          "description": "HPF"
        },
        {
          "name": "forestcaver",
          "url": "https://raw.githubusercontent.com/forestcaver/Analog-Voice/master/images/AJH_ASR_01.jpg",
          "description": "Dual ASR"
        },
        {
          "name": "forestcaver",
          "url": "https://raw.githubusercontent.com/forestcaver/Analog-Voice/master/images/013-modular_ajh_vca1.jpg",
          "description": "Dual VCA"
        },
        {
          "name": "forestcaver",
          "url": "https://raw.githubusercontent.com/forestcaver/Analog-Voice/master/images/018-modular_ajh_wasp.jpg",
          "description": "Wasp"
        },
        {
          "name": "forestcaver",
          "url": "https://raw.githubusercontent.com/forestcaver/Analog-Voice/master/images/020-modular_ajh_adsr.jpg",
          "description": "ADSR"
        },
        {
          "name": "forestcaver",
          "url": "https://raw.githubusercontent.com/forestcaver/Analog-Voice/master/images/022-modular_ajh_lpf2.jpg",
          "description": "LPF 2"
        },
        {
          "name": "forestcaver",
          "url": "https://raw.githubusercontent.com/forestcaver/Analog-Voice/master/images/024-modular_ajh_module_tester.jpg",
          "description": "Module Tester Module"
        },
        {
          "name": "forestcaver",
          "url": "https://raw.githubusercontent.com/forestcaver/Analog-Voice/master/images/2B_01.jpg",
          "description": "Dual polarising VCA"
        },
        {
          "name": "forestcaver",
          "url": "https://raw.githubusercontent.com/forestcaver/Analog-Voice/master/images/025-modular_ajh_mm.jpg",
          "description": "Matrix Mixer"
        },
        {
          "name": "forestcaver",
          "url": "https://raw.githubusercontent.com/forestcaver/Analog-Voice/master/images/027-modular_ajh_tzfm.jpg",
          "description": "TZFM VCO"
        }
      ]
    }]
  },
  {
    "name" : "nickajeglin",
    "urls" : ["https://github.com/nickajeglin"],
    "descriptions" : [],
    "repos": [{
      "name" : "Eurorack-pcbs",
      "url" : "https://github.com/nickajeglin/Eurorack-pcbs",
      "links" : [],
      "descriptions" : [
        "A collection of easy to solder DIY eurorack PCB's",
        "* Dual log/lin VCA",
        "* Mixer",
        "* Utility LFO (8K LFO)",
        "* Buffered Mult",
        "* Analog Logic"
      ],
      "images" : [
        {
          "name": "nickajeglin",
          "url": "https://camo.githubusercontent.com/5b1760cff7b9dff9be71aec076da5dda8e5dce89064a7f443aac20dc635885a7/68747470733a2f2f692e696d6775722e636f6d2f6a6a434c5751392e6a7067",
          "description": "Dual log/lin VCA"
        },
        {
          "name": "nickajeglin",
          "url": "https://camo.githubusercontent.com/1ea63cfa206ecdca427462512b22c566d6f25c53e876bfb12f6dd28b5391e29c/68747470733a2f2f692e696d6775722e636f6d2f355263506f41492e6a7067",
          "description": "VCO"
        },
        {
          "name": "nickajeglin",
          "url": "https://camo.githubusercontent.com/0e27c73b4cef917e7785c864acca316ad71467816eb81c270669f83a3a6b2d2d/68747470733a2f2f692e696d6775722e636f6d2f4239554f4a78472e706e67",
          "description": "Utility LFO (8K LFO)"
        },
        {
          "name": "nickajeglin",
          "url": "https://camo.githubusercontent.com/99022575f6bb3d83c71c00298ab3731fbe999e73b0bc7277c2074f31df5c5cfd/68747470733a2f2f692e696d6775722e636f6d2f4e4a774565314a2e6a7067",
          "description": "Buffered Mult"
        },
        {
          "name": "nickajeglin",
          "url": "https://camo.githubusercontent.com/e447cf438ad0416cb6319f24f0cd35e43819a3e6daaefb8f46a1e8d187c1daa3/68747470733a2f2f696d6775722e636f6d2f726f32706934322e706e67",
          "description": "Analog Logic"
        }]
    }]
  },
  {
  "name" : "shaduzlabs",
  "urls" : ["https://github.com/shaduzlabs"],
  "descriptions" : [],
  "repos": [{
    "name" : "synapse",
    "url" : "https://github.com/shaduzlabs/synapse",
    "links" : ["http://ornament-and-cri.me/hardware-basics/"],
    "descriptions" : [
      "Synapse is an Arduino shield (and corresponding library) which provides CV and Gate I/O for Arduino boards."
    ],
    "images" :  [
      {
        "name": "synapse",
        "url": "https://cloud.githubusercontent.com/assets/804931/13776151/e4bdfa4c-eaa8-11e5-8b88-48274cfd1437.png",
        "description": "synapse CV / Gate / IO shield"
      }
    ]
  }]
},
  {
  "name" : "mxmxmx",
  "urls" : ["https://github.com/mxmxmx"],
  "descriptions" : [],
  "repos":
  [
    {
      "name": "O_C",
      "url" : "https://github.com/mxmxmx/O_C",
      "links" : ["http://ornament-and-cri.me/hardware-basics/"],
      "descriptions" : [
        "eurorack / teensy 3.2 DAC8565 quad 16bit CV module w/ OLED display"
      ],
      "images" :  [
        {
          "name": "ornament & crime",
          "url": "https://camo.githubusercontent.com/b6298b40092d76718e4314e94591550e0d4197768af020ecb196b9408b2f2385/68747470733a2f2f6661726d312e737461746963666c69636b722e636f6d2f3637362f32303039303737343639345f623536653535373639335f622e6a7067",
          "description": "polymorphic CV generator"
        }
      ]
    },
    {
      "name": "CV2Midi",
      "url" : "https://github.com/mxmxmx/CV2Midi",
      "links" : [],
      "descriptions" : [
        "5 channel CV midi converter"
      ],
      "images" :  [
      {
        "name": "5 channel CV",
        "url": "https://camo.githubusercontent.com/d73a47d49de1f8e1ead6e8de8f84320f2114b97acd9962a00a78c872fa813d0a/68747470733a2f2f63322e737461746963666c69636b722e636f6d2f322f313738302f34333130353234363031355f386363363031663762655f682e6a7067",
        "description": "midi converter"
      }]
    },
    {
      "name": "minitrash",
      "url" : "https://github.com/mxmxmx/minitrash",
      "links" : [],
      "descriptions" : [
        "6HP teensy 3.1 / wm8731 codec thingie"
      ],
      "images" :  [
        {
          "name": "6HP teensy 3.1",
          "url": "https://camo.githubusercontent.com/936e2fdd8f250eafafeeed567bce8637c7039ab33bf71d702f1b206476d4bbac/68747470733a2f2f63322e737461746963666c69636b722e636f6d2f322f313633342f32343236373135333338335f343132386364366461315f632e6a7067",
          "description": "wm8731 codec thingie"
        }]
    },
    {
      "name": "terminal_tedium",
      "url" : "https://github.com/mxmxmx/terminal_tedium",
      "links" : [],
      "descriptions" : [
        "raspberry pi eurorack breakout"
      ],
      "images" :  [
        {
          "name": "terminal_tedium",
          "url": "https://camo.githubusercontent.com/0193279a89040295a88d76e2db4238a461a1c33cd1146fc0513b8fbb382a1023/68747470733a2f2f6661726d312e737461746963666c69636b722e636f6d2f3432332f31393238303139343134365f343536383737306463665f632e6a7067",
          "description": "raspberry pi eurorack breakout"
        }]
    }
  ]
},
  {
    "name" : "bastl-instruments",
    "urls" : ["https://github.com/bastl-instruments"],
    "descriptions" : [],
    "repos": [{
      "name" : "kastle",
      "url" : "https://github.com/bastl-instruments/kastle",
      "links" : [],
      "descriptions" : ["(discontinued) mini modular synthesizer"],
      "images" :  [
        {
          "name": "Kastle",
          "url": "https://bastl-instruments.com/thumbs/instruments/kastle/kastle-synth/kastle_synth_01_product-400x330.jpg",
          "description": "mini modular synthesizer"
        }]
    }]
  },
  {
    "name" : "kweiwen",
    "urls" : ["https://github.com/kweiwen"],
    "descriptions" : [],
    "repos": [{
      "name" : "benjolin",
      "url" : "https://github.com/kweiwen/benjolin",
      "links" : [],
      "descriptions" : ["diy eurorack project based on rob hordijks benjolin"],
      "images" :  [
        {
          "name": "benjolin",
          "url": "https://cloud.githubusercontent.com/assets/15021145/25553005/d3c58190-2cda-11e7-86a0-99eca499a703.JPG",
          "description": "diy eurorack project based on rob hordijks benjolin"
        }]
      },
      {
        "name" : "thinks",
        "url" : "https://github.com/kweiwen/thinks",
        "links" : [],
        "descriptions" : ["a modification eurorack project based on mutable links"],
        "images" :  [
          {
            "name": "thinks",
            "url": "https://user-images.githubusercontent.com/15021145/30574703-72b73fa0-9d2e-11e7-863c-96f330bda927.jpg",
            "description": " based on mutable links"
          }]
      }]
  },
  {
    "name" : "cutlasses",
    "urls" : ["https://github.com/cutlasses"],
    "descriptions" : [],
    "repos": [{
      "name" : "AudioFreezeV2",
      "url" : "https://github.com/cutlasses/AudioFreezeV2",
      "links" : [],
      "descriptions" : ["AudioFreeze Teensy based Eurorack module"],
      "images" :  [
      {
        "name": "AudioFreeze",
        "url": "https://camo.githubusercontent.com/12c7071affaf41cf822eb3812b3b2d2a77fd12df29681fda7ac2170e09257e49/687474703a2f2f696d672e796f75747562652e636f6d2f76692f6769622d5552706c4a78492f302e6a7067",
        "description": "AudioFreeze Teensy based Eurorack module"
      }]
    }]
  },
  {
    "name" : "mattb",
    "urls" : ["https://github.com/mattb"],
    "descriptions" : [],
    "repos": [{
      "name" : "teensy-cv",
      "url" : "https://github.com/mattb/teensy-cv",
      "links" : [],
      "descriptions" : [
        "An opamp board with attenuating pots on inputs to",
        " * scale -5/+5V control voltage signals down to a voltage-referenced 0-2.5v range",
        " * scale up output to -5/+5V range"],
      "images" :  [
      {
        "name": "teensy-cv",
        "url": "https://raw.githubusercontent.com/mattb/teensy-cv/master/teensy-cv-schematic.png",
        "description": "circuit"
      },
        {
          "name": "teensy-cv",
          "url": "https://raw.githubusercontent.com/mattb/teensy-cv/master/teensy-cv-pcb.png",
          "description": "pcb"
        }]
    }]
  },
  {
    "name" : "little-scale",
    "urls" : ["https://github.com/little-scale"],
    "descriptions" : [],
    "repos": [{
      "name" : "eurorack",
      "url" : "https://github.com/little-scale/eurorack",
      "links" : [],
      "descriptions" : [],
      "images" : []
    }]
  },
  {
    "name" : "ThoEvans",
    "urls" : ["https://github.com/ThoEvans"],
    "descriptions" : [],
    "repos": [{
      "name" : "Eurorack",
      "url" : "https://github.com/ThoEvans/Eurorack",
      "links" : [],
      "descriptions" : ["Hardware design for Eurorack modular synthesizers", " * Dual LPF"," * Stereo Mixer Euro"," * Stereo VCA"],
      "images" :  [
        {
          "name": "ThoEvans",
          "url": "https://raw.githubusercontent.com/ThoEvans/Eurorack/master/Dual%20LPF/Dual%20LPF%20Schematic.png",
          "description": "Dual LPF"
        },
        {
          "name" : "ThoEvans",
          "url": "https://raw.githubusercontent.com/ThoEvans/Eurorack/master/Stereo%20Mixer%20Euro/Stereo%20Mixer%20Schematic.png",
          "description": "Stereo Mixer Euro"
        },
        {
          "name": "ThoEvans",
          "url": "https://raw.githubusercontent.com/ThoEvans/Eurorack/master/Stereo%20VCA/Stereo%20VCA%20Schematic.png",
          "description": "Stereo VCA"
        }
      ]
    }]
  },
  {
    "name" : "ctag-fh-kiel",
    "urls" : ["https://github.com/ctag-fh-kiel"],
    "descriptions" : [],
    "repos": [{
      "name" : "ctag-straempler",
      "url" : "https://github.com/ctag-fh-kiel/ctag-straempler",
      "links" : [],
      "descriptions" : [
        "ESP32 Eurorack Audio Synthesis Module"
      ],
      "images" : [{
        "name": "ctag-fh-kiel",
        "url": "https://raw.githubusercontent.com/wiki/ctag-fh-kiel/ctag-straempler/img/straempler-boot.jpg",
        "description": "CTAG Straempler"
      }]
    }]
  },
  {
    "name" : "minisystem",
    "urls" : ["https://github.com/minisystem"],
    "descriptions" : [],
    "repos": [{
      "name" : "Eurorack",
      "url" : "https://github.com/minisystem/Eurorack",
      "links" : [],
      "descriptions" : ["Kicad designs for eurorack modules"," * Eurorack Mixer", " * Eurorack VCA", " * Octave Switch", " * VC ADSR", " * picoVCO - corrected"],
      "images" : []
    },{
      "name" : "JOVE",
      "url" : "https://github.com/minisystem/JOVE",
      "links" : [],
      "descriptions" : ["Roland Jupiter 6 inspired multimode filter in 14HP Eurorack format"],
      "images" : []
    }]
  },
  {
    "name" : "TomWhitwell",
    "urls" : ["https://github.com/TomWhitwell"],
    "descriptions" : [],
    "repos": [{
      "name" : "TH-VCO1",
      "url" : "https://github.com/TomWhitwell/TH-VCO1",
      "links" : [],
      "descriptions" : [
        "Eurorack Layout for the Thomas Henry VCO 1 Oscillator"
      ],
      "images" : []
    }]
  },
  {
    "name" : "16n-faderbank",
    "urls" : ["https://github.com/16n-faderbank"],
    "descriptions" : [],
    "repos": [{
      "name" : "16n",
      "url" : "https://github.com/16n-faderbank/16n",
      "links" : [],
      "descriptions" : [
        "Sixteen faders, a Teensy, MIDI over USB and jack, CV out, and I2C out"
      ],
      "images" : [{
      "name": "16n-faderbank",
      "url": "https://raw.githubusercontent.com/16n-faderbank/16n/main/faderbank.jpg",
      "description": "16n"
    }]
    }]
  },
  {
    "name" : "jkrame1",
    "urls" : ["https://github.com/jkrame1"],
    "descriptions" : [],
    "repos": [{
      "name" : "Betweener",
      "url" : "https://github.com/jkrame1/Betweener",
      "links" : [],
      "descriptions" : ["Teensy 3.2 based Eurorack DIY module", "* 4 built-in control voltage (CV) inputs", " * 4 trigger inputs", " * 4 knobs", " * 4 CV outputs"],
      "images" : [{
        "name": "ctag-fh-kiel",
        "url": "https://raw.githubusercontent.com/jkrame1/Betweener/master/Hardware/Betweener%20Build%20Images/Betweener-75.jpg",
        "description": "Betweener"
      }]
    }]
  },
  {
    "name" : "hermflink",
    "urls" : ["https://github.com/hermflink"],
    "descriptions" : [],
    "repos": [
      {
        "name" : "3320VCF",
        "url" : "https://github.com/hermflink/3320VCF",
        "links" : [],
        "descriptions" : [
          "Kicad project files of a CEM3320/AS3320 based VCF"
        ],
        "images" : []
      },
      {
        "name" : "3330VCA",
        "url" : "https://github.com/hermflink/3330VCA",
        "links" : [],
        "descriptions" : [
          "Kicad project files of a AS3330 based dual VCA"
        ],
        "images" : []
      },
      {
        "name" : "3310ADSR",
        "url" : "https://github.com/hermflink/3310ADSR",
        "links" : [],
        "descriptions" : [
          "Kicad project files of a dual ADSR based on two AS3310 components"
        ],
        "images" : []
      },
      {
        "name" : "VCO1",
        "url" : "https://github.com/hermflink/VCO1",
        "links" : [],
        "descriptions" : [
          "Kicad files of a Voltage controlled oscillator with saw, pulse and triangle outputs."
        ],
        "images" : []
      }
    ]
  },
  {
    "name" : "covertneko",
    "urls" : ["https://github.com/covertneko"],
    "descriptions" : [],
    "repos": [
      {
        "name" : "vcf-20",
        "url" : "https://github.com/covertneko/vcf-20",
        "links" : [],
        "descriptions" : [
          "Kicad project files for a compact multimode eurorack filter with MS-20 style resonance."
        ],
        "images" : []
    }]
  },
  {
    "name" : "matthewcieplak",
    "urls" : ["https://github.com/matthewcieplak"],
    "descriptions" : [],
    "repos": [
      {
        "name" : "super-sixteen",
        "url" : "https://github.com/matthewcieplak/super-sixteen",
        "links" : [],
        "descriptions" : [
          "open-source/open-hardware sequencer for the Eurorack synthesizer format"
        ],
        "images" : [{
          "name": "matthewcieplak",
          "url": "https://camo.githubusercontent.com/46c538cadf57bc482dfb7e2370e2b374a3ac7be3d1519428b34549e951a78f89/68747470733a2f2f73332e616d617a6f6e6177732e636f6d2f65787472616c696665696e737472756d656e74732e636f6d2f696d616765732f70726f647563742f73757065727369787465656e2d6d6574616c2e6a7067",
          "description": "super-sixteen"
      }]
    }]
  },
  {
    "name" : "attoparsec",
    "urls" : ["https://github.com/attoparsec"],
    "descriptions" : [],
    "repos": [
      {
        "name" : "TruthTable",
        "url" : "https://github.com/attoparsec/TruthTable",
        "links" : ["https://youtu.be/MvsgOZwyrD4"],
        "descriptions" : ["Eurorack Truth Table module"],
        "images" : []
      },
      {
        "name" : "Node",
        "url" : "https://github.com/attoparsec/Node",
        "links" : [],
        "descriptions" : [],
        "images" : []
      }]
  }
]
